topsis_prigya_102313061/__init__.py
topsis_prigya_102313061/topsis.py
topsis_prigya_102313061-1.0.3.dist-info/licenses/LICENSE
topsis_prigya_102313061-1.0.3.dist-info/METADATA
topsis_prigya_102313061-1.0.3.dist-info/WHEEL
topsis_prigya_102313061-1.0.3.dist-info/entry_points.txt
topsis_prigya_102313061-1.0.3.dist-info/top_level.txt
topsis_prigya_102313061-1.0.3.dist-info/RECORD
