Metadata-Version: 2.4
Name: Topsis-Prigya-102313061
Version: 1.0.3
Summary: Command line implementation of TOPSIS method
Author: Prigya Goyal
Author-email: goyalprigya@gmail.com
Requires-Python: >=3.6
License-File: LICENSE
Requires-Dist: pandas
Requires-Dist: numpy
Dynamic: author
Dynamic: author-email
Dynamic: description
Dynamic: description-content-type
Dynamic: license-file
Dynamic: requires-dist
Dynamic: requires-python
Dynamic: summary
